{
  "key": "group_666eb7f38d2ed",
  "title": "Page Title",
  "fields": [
      {
          "key": "field_666eb7f40c492",
          "label": "Page Title",
          "name": "page_title_display",
          "aria-label": "",
          "type": "select",
          "instructions": "",
          "required": 0,
          "conditional_logic": 0,
          "wrapper": {
              "width": "",
              "class": "",
              "id": ""
          },
          "choices": {
              "show": "Show",
              "hide-visually": "Hide visually",
              "hide": "Hide"
          },
          "default_value": "show",
          "return_format": "value",
          "multiple": 0,
          "allow_null": 0,
          "ui": 0,
          "ajax": 0,
          "placeholder": ""
      }
  ],
  "location": [
      [
          {
              "param": "post_type",
              "operator": "==",
              "value": "post"
          }
      ],
      [
          {
              "param": "post_type",
              "operator": "==",
              "value": "page"
          }
      ]
  ],
  "menu_order": -10,
  "position": "side",
  "style": "default",
  "label_placement": "top",
  "instruction_placement": "label",
  "hide_on_screen": "",
  "active": true,
  "description": "",
  "show_in_rest": 0,
  "modified": 1725978564
}
